mlflow_greenplum/__init__.py
mlflow_greenplum/artifacts.py
mlflow_greenplum/models.py
mlflow_greenplum/patching.py
mlflow_greenplum/registry.py
mlflow_greenplum/store.py
mlflow_greenplum_plugin-0.1.0.dist-info/LICENSE
mlflow_greenplum_plugin-0.1.0.dist-info/METADATA
mlflow_greenplum_plugin-0.1.0.dist-info/NOTICE
mlflow_greenplum_plugin-0.1.0.dist-info/WHEEL
mlflow_greenplum_plugin-0.1.0.dist-info/entry_points.txt
mlflow_greenplum_plugin-0.1.0.dist-info/top_level.txt
mlflow_greenplum_plugin-0.1.0.dist-info/RECORD
