Metadata-Version: 2.1
Name: mlflow-greenplum-plugin
Version: 0.1.0
Summary: MLflow plugin for Greenplum database support
Author: Russ Russell
Author-email: Russ Russell <625ruslan@gmail.com>
License: Apache-2.0
Project-URL: Homepage, https://github.com/Parsifal626/mlflow_plugin
Project-URL: Documentation, https://github.com/Parsifal626/mlflow_plugin#readme
Project-URL: Repository, https://github.com/Parsifal626/mlflow_plugin.git
Project-URL: Bug Tracker, https://github.com/Parsifal626/mlflow_plugin/issues
Keywords: mlflow,greenplum,machine-learning,tracking
Classifier: Development Status :: 3 - Alpha
Classifier: Intended Audience :: Developers
Classifier: License :: OSI Approved :: Apache Software License
Classifier: Programming Language :: Python :: 3
Classifier: Programming Language :: Python :: 3.8
Classifier: Programming Language :: Python :: 3.9
Classifier: Programming Language :: Python :: 3.10
Classifier: Topic :: Scientific/Engineering :: Artificial Intelligence
Classifier: Topic :: Database
Requires-Python: >=3.8
License-File: LICENSE
License-File: NOTICE
Requires-Dist: mlflow>=2.0.0
Requires-Dist: sqlalchemy<2.0.0,>=1.4.0
Requires-Dist: alembic>=1.7.0
Requires-Dist: psycopg2>=2.8.6
Provides-Extra: dev
Requires-Dist: pytest>=6.0.0; extra == "dev"
Requires-Dist: pytest-cov>=2.10.0; extra == "dev"
Requires-Dist: black>=21.0.0; extra == "dev"
Requires-Dist: flake8>=3.9.0; extra == "dev"
Requires-Dist: mypy>=0.900; extra == "dev"
